plain/toolbar/CHANGELOG.md
plain/toolbar/README.md
plain/toolbar/__init__.py
plain/toolbar/config.py
plain/toolbar/exceptions.py
plain/toolbar/registry.py
plain/toolbar/templates.py
plain/toolbar/toolbar.py
plain/toolbar/assets/toolbar/toolbar.js
plain/toolbar/templates/toolbar/exception.html
plain/toolbar/templates/toolbar/exception_button.html
plain/toolbar/templates/toolbar/request.html
plain/toolbar/templates/toolbar/toolbar.html
plain_toolbar-0.10.0.dist-info/METADATA
plain_toolbar-0.10.0.dist-info/WHEEL
plain_toolbar-0.10.0.dist-info/licenses/LICENSE
plain_toolbar-0.10.0.dist-info/RECORD
