Metadata-Version: 2.4
Name: plain.toolbar
Version: 0.10.0
Summary: Debug toolbar for Plain applications
Author-email: Dave Gaeddert <dave.gaeddert@dropseed.dev>
License-Expression: BSD-3-Clause
License-File: LICENSE
Requires-Python: >=3.13
Requires-Dist: plain-tailwind<1.0.0
Requires-Dist: plain<1.0.0
